<?xml version="1.0" encoding="UTF-8"?>
<objects serializationModel="Studio.02.02.00">
	<object class="AudioFile" id="{e9b1eb31-a03c-49b5-9222-3a335feab92a}">
		<property name="assetPath">
			<value>19988__acclivity__fingerplop3.flac</value>
		</property>
		<property name="frequencyInKHz">
			<value>44.0999985</value>
		</property>
		<property name="channelCount">
			<value>2</value>
		</property>
		<property name="length">
			<value>0.14351473922902494</value>
		</property>
		<relationship name="masterAssetFolder">
			<destination>{c38116e8-12a0-43eb-a113-ef2fa82b8d79}</destination>
		</relationship>
	</object>
</objects>
